htpayway/__init__.py
htpayway/admin.py
htpayway/apps.py
htpayway/config.py
htpayway/forms.py
htpayway/models.py
htpayway/tests.py
htpayway/urls.py
htpayway/utils.py
htpayway/views.py
htpayway/migrations/0001_initial.py
htpayway/migrations/__init__.py
htpayway/templates/htpayway/base.html
htpayway/templates/htpayway/begin.html
htpayway/templates/htpayway/failure.html
htpayway/templates/htpayway/payway-form.html
htpayway/templates/htpayway/success.html
django_htpayway-1.0.0.dist-info/METADATA
django_htpayway-1.0.0.dist-info/WHEEL
django_htpayway-1.0.0.dist-info/licenses/LICENSE
django_htpayway-1.0.0.dist-info/RECORD
